fluidsdk/__init__.py
fluidsdk/conversational_modules.py
fluidsdk/conversations_v3.py
fluidsdk/flow.py
fluidsdk/intents.py
fluidsdk/macros.py
fluidsdk/message.py
fluidsdk/status_webhook.py
fluidsdk/templates.py
fluidsdk/pyrite/__init__.py
fluidsdk/pyrite/builder.py
fluidsdk/pyrite/consts.py
fluidsdk/pyrite/library.py
fluidsdk/pyrite/message.py
fluidsdk/pyrite/regex_library.py
fluidsdk/pyrite/utils.py
fluidsdk-0.4.6.dist-info/METADATA
fluidsdk-0.4.6.dist-info/WHEEL
fluidsdk-0.4.6.dist-info/licenses/LICENSE
fluidsdk-0.4.6.dist-info/RECORD
